{
  "IcoMoonType": "selection",
  "icons": [
    {
      "icon": {
        "paths": [
          "M852.542 65.065h-681.084c-58.605 0-106.114 47.509-106.114 106.114l-0 681.643c0 58.605 47.509 106.114 106.114 106.114h681.084c58.605 0 106.114-47.509 106.114-106.114v-681.643c0-58.605-47.509-106.114-106.114-106.114zM735.258 176.764h83.774c15.422 0 27.925 12.502 27.925 27.925v83.774c0 15.422-12.502 27.925-27.925 27.925h-83.774c-15.422 0-27.925-12.502-27.925-27.925v-83.774c-0-15.422 12.502-27.925 27.925-27.925zM511.86 341.519c94.573 0.159 171.179 76.862 171.179 171.458 0 94.694-76.764 171.458-171.458 171.458s-171.458-76.764-171.458-171.458c0.157-94.729 76.986-171.462 171.737-171.462 0.393 0 0.785 0.001 1.178 0.004zM846.957 874.882h-670.194c-15.422 0-27.925-12.502-27.925-27.925v-418.871h111.699c-12.349 23.021-19.603 50.366-19.603 79.405 0 1.536 0.020 3.068 0.061 4.595-0.005 149.912 121.705 271.622 271.843 271.622s271.847-121.71 271.847-271.847c0.143-2.393 0.224-5.191 0.224-8.007 0-28.076-8.093-54.263-22.073-76.353l112.046 0.586v418.871c-0 15.422-12.502 27.925-27.925 27.925z"
        ],
        "attrs": [
          {
            "fill": "rgb(255, 255, 255)"
          }
        ],
        "isMulticolor": false,
        "isMulticolor2": false,
        "grid": 0,
        "tags": [
          "holdingwebpage-04"
        ]
      },
      "attrs": [
        {
          "fill": "rgb(255, 255, 255)"
        }
      ],
      "properties": {
        "order": 7,
        "id": 1,
        "name": "instagram",
        "prevSize": 32,
        "code": 59648
      },
      "setIdx": 0,
      "setId": 2,
      "iconIdx": 1
    },
    {
      "icon": {
        "paths": [
          "M49.427 336.214h215.858v616.578h-215.858v-616.578z",
          "M265.285 135.714c0 59.53-48.259 107.789-107.789 107.789s-107.789-48.259-107.789-107.789c0-59.53 48.259-107.789 107.789-107.789s107.789 48.259 107.789 107.789z",
          "M974.573 614.344c0-167.548-36.023-277.851-229.821-277.851-93.269 0-155.82 34.627-181.511 83.774h-2.792v-85.17h-171.737v617.695h179.556v-305.497c0-80.702 15.359-158.612 115.050-158.612s106.114 92.152 106.114 163.918v300.191h185.141v-338.448z"
        ],
        "attrs": [
          {
            "fill": "rgb(255, 255, 255)"
          },
          {
            "fill": "rgb(255, 255, 255)"
          },
          {
            "fill": "rgb(255, 255, 255)"
          }
        ],
        "isMulticolor": false,
        "isMulticolor2": false,
        "grid": 0,
        "tags": [
          "holdingwebpage-05"
        ]
      },
      "attrs": [
        {
          "fill": "rgb(255, 255, 255)"
        },
        {
          "fill": "rgb(255, 255, 255)"
        },
        {
          "fill": "rgb(255, 255, 255)"
        }
      ],
      "properties": {
        "order": 6,
        "id": 0,
        "name": "linkedin",
        "prevSize": 32,
        "code": 59649
      },
      "setIdx": 0,
      "setId": 2,
      "iconIdx": 2
    }
  ],
  "height": 1024,
  "metadata": {
    "name": "icomoon"
  },
  "preferences": {
    "showGlyphs": true,
    "showQuickUse": true,
    "showQuickUse2": true,
    "showSVGs": true,
    "fontPref": {
      "prefix": "icon-",
      "metadata": {
        "fontFamily": "icomoon"
      },
      "metrics": {
        "emSize": 1024,
        "baseline": 6.25,
        "whitespace": 50
      },
      "embed": false
    },
    "imagePref": {
      "prefix": "icon-",
      "png": true,
      "useClassSelector": true,
      "color": 0,
      "bgColor": 16777215,
      "classSelector": ".icon"
    },
    "historySize": 100,
    "showCodes": true,
    "gridSize": 16
  }
}